loopyng/__init__.py
loopyng/lite_sample_sounds.py
loopyng/util.py
loopyng/examples/__init__.py
loopyng/examples/annotated_sounds.py
loopyng/examples/tagged_intervals.py
loopyng/gen/__init__.py
loopyng/gen/diagnosis_sounds.py
loopyng/gen/signal_generators.py
loopyng/gen/simple.py
loopyng/gen/sine_mix.py
loopyng/gen/util.py
loopyng/gen/voiced_time.py
loopyng/scrap/__init__.py
loopyng/sound/__init__.py
loopyng/sound/audio.py
loopyng/sound/audio_librosa.py
loopyng/utils/__init__.py
loopyng/utils/date_ticks.py
loopyng/utils/infinite_waveform.py
loopyng/utils/librosa_utils.py
loopyng/utils/plotting.py
loopyng-0.1.35.dist-info/LICENSE
loopyng-0.1.35.dist-info/METADATA
loopyng-0.1.35.dist-info/WHEEL
loopyng-0.1.35.dist-info/top_level.txt
loopyng-0.1.35.dist-info/RECORD
