Metadata-Version: 2.1
Name: loopyng
Version: 0.1.35
Summary: Generate synthetic signals for ML pipelines
Home-page: https://github.com/thorwhalen/loopyng
License: mit
Keywords: data,signal processing,audio
Platform: any
License-File: LICENSE
Requires-Dist: argh
Requires-Dist: IPython
Requires-Dist: matplotlib
Requires-Dist: numpy
Requires-Dist: packaging
Requires-Dist: pandas
Requires-Dist: scipy
Requires-Dist: soundfile
Requires-Dist: scikit-learn
Requires-Dist: i2
Requires-Dist: slink
Requires-Dist: more-itertools
